{"flowContents":{"identifier":"2ecb96c9-8f15-384f-8cc3-87b24e77c57c","instanceIdentifier":"b56d05a9-0199-1000-7fa1-5846e3b77504","name":"gemini_v1","comments":"","position":{"x":934.1424493747612,"y":155.41037388534767},"processGroups":[],"remoteProcessGroups":[],"processors":[{"identifier":"e1d2e942-6fac-3bb8-807b-f6fa80c2cd41","instanceIdentifier":"b575a029-0199-1000-4567-3787e8702850","name":"PutFile","comments":"","position":{"x":366.97767124318136,"y":761.2481224419474},"type":"org.apache.nifi.processors.standard.PutFile","bundle":{"group":"org.apache.nifi","artifact":"nifi-standard-nar","version":"2.5.0"},"properties":{"Group":null,"Owner":null,"Create Missing Directories":"true","Permissions":null,"Maximum File Count":null,"Last Modified Time":null,"Directory":"E:\\logs","Conflict Resolution Strategy":"fail"},"propertyDescriptors":{"Group":{"name":"Group","displayName":"Group","identifiesControllerService":false,"sensitive":false,"dynamic":false},"Owner":{"name":"Owner","displayName":"Owner","identifiesControllerService":false,"sensitive":false,"dynamic":false},"Create Missing Directories":{"name":"Create Missing Directories","displayName":"Create Missing Directories","identifiesControllerService":false,"sensitive":false,"dynamic":false},"Permissions":{"name":"Permissions","displayName":"Permissions","identifiesControllerService":false,"sensitive":false,"dynamic":false},"Maximum File Count":{"name":"Maximum File Count","displayName":"Maximum File Count","identifiesControllerService":false,"sensitive":false,"dynamic":false},"Last Modified Time":{"name":"Last Modified Time","displayName":"Last Modified Time","identifiesControllerService":false,"sensitive":false,"dynamic":false},"Directory":{"name":"Directory","displayName":"Directory","identifiesControllerService":false,"sensitive":false,"dynamic":false},"Conflict Resolution Strategy":{"name":"Conflict Resolution Strategy","displayName":"Conflict Resolution Strategy","identifiesControllerService":false,"sensitive":false,"dynamic":false}},"style":{},"schedulingPeriod":"0 sec","schedulingStrategy":"TIMER_DRIVEN","executionNode":"ALL","penaltyDuration":"30 sec","yieldDuration":"1 sec","bulletinLevel":"WARN","runDurationMillis":0,"concurrentlySchedulableTaskCount":1,"autoTerminatedRelationships":["success","failure"],"scheduledState":"ENABLED","retryCount":10,"retriedRelationships":[],"backoffMechanism":"PENALIZE_FLOWFILE","maxBackoffPeriod":"10 mins","componentType":"PROCESSOR","groupIdentifier":"2ecb96c9-8f15-384f-8cc3-87b24e77c57c"},{"identifier":"3693d146-fa41-3628-9cf0-cb1e64a80b7e","instanceIdentifier":"b56d2487-0199-1000-a9af-363f0d1c43ff","name":"ListFile","comments":"","position":{"x":-298.9999741265399,"y":-151.7999670869632},"type":"org.apache.nifi.processors.standard.ListFile","bundle":{"group":"org.apache.nifi","artifact":"nifi-standard-nar","version":"2.5.0"},"properties":{"Minimum File Age":"0 sec","et-initial-listing-target":"all","Maximum File Age":null,"max-listing-time":"3 mins","record-writer":null,"Maximum File Size":null,"et-time-window":"3 hours","et-node-identifier":"${hostname()}","Recurse Subdirectories":"true","File Filter":"[^\\.].*","Path Filter":null,"Include File Attributes":"true","Input Directory Location":"Local","listing-strategy":"timestamps","Input Directory":"E:\\nifi-source\\gemini","target-system-timestamp-precision":"auto-detect","track-performance":"false","max-performance-metrics":"100000","Minimum File Size":"0 B","Ignore Hidden Files":"true","et-state-cache":null,"max-operation-time":"10 secs"},"propertyDescriptors":{"Minimum File Age":{"name":"Minimum File Age","displayName":"Minimum File Age","identifiesControllerService":false,"sensitive":false,"dynamic":false},"et-initial-listing-target":{"name":"et-initial-listing-target","displayName":"Entity Tracking Initial Listing Target","identifiesControllerService":false,"sensitive":false,"dynamic":false},"Maximum File Age":{"name":"Maximum File Age","displayName":"Maximum File Age","identifiesControllerService":false,"sensitive":false,"dynamic":false},"max-listing-time":{"name":"max-listing-time","displayName":"Max Directory Listing Time","identifiesControllerService":false,"sensitive":false,"dynamic":false},"record-writer":{"name":"record-writer","displayName":"Record Writer","identifiesControllerService":true,"sensitive":false,"dynamic":false},"Maximum File Size":{"name":"Maximum File Size","displayName":"Maximum File Size","identifiesControllerService":false,"sensitive":false,"dynamic":false},"et-time-window":{"name":"et-time-window","displayName":"Entity Tracking Time Window","identifiesControllerService":false,"sensitive":false,"dynamic":false},"et-node-identifier":{"name":"et-node-identifier","displayName":"Entity Tracking Node Identifier","identifiesControllerService":false,"sensitive":false,"dynamic":false},"Recurse Subdirectories":{"name":"Recurse Subdirectories","displayName":"Recurse Subdirectories","identifiesControllerService":false,"sensitive":false,"dynamic":false},"File Filter":{"name":"File Filter","displayName":"File Filter","identifiesControllerService":false,"sensitive":false,"dynamic":false},"Path Filter":{"name":"Path Filter","displayName":"Path Filter","identifiesControllerService":false,"sensitive":false,"dynamic":false},"Include File Attributes":{"name":"Include File Attributes","displayName":"Include File Attributes","identifiesControllerService":false,"sensitive":false,"dynamic":false},"Input Directory Location":{"name":"Input Directory Location","displayName":"Input Directory Location","identifiesControllerService":false,"sensitive":false,"dynamic":false},"listing-strategy":{"name":"listing-strategy","displayName":"Listing Strategy","identifiesControllerService":false,"sensitive":false,"dynamic":false},"Input Directory":{"name":"Input Directory","displayName":"Input Directory","identifiesControllerService":false,"sensitive":false,"dynamic":false},"target-system-timestamp-precision":{"name":"target-system-timestamp-precision","displayName":"Target System Timestamp Precision","identifiesControllerService":false,"sensitive":false,"dynamic":false},"track-performance":{"name":"track-performance","displayName":"Track Performance","identifiesControllerService":false,"sensitive":false,"dynamic":false},"max-performance-metrics":{"name":"max-performance-metrics","displayName":"Maximum Number of Files to Track","identifiesControllerService":false,"sensitive":false,"dynamic":false},"Minimum File Size":{"name":"Minimum File Size","displayName":"Minimum File Size","identifiesControllerService":false,"sensitive":false,"dynamic":false},"Ignore Hidden Files":{"name":"Ignore Hidden Files","displayName":"Ignore Hidden Files","identifiesControllerService":false,"sensitive":false,"dynamic":false},"et-state-cache":{"name":"et-state-cache","displayName":"Entity Tracking State Cache","identifiesControllerService":true,"sensitive":false,"dynamic":false},"max-operation-time":{"name":"max-operation-time","displayName":"Max Disk Operation Time","identifiesControllerService":false,"sensitive":false,"dynamic":false}},"style":{},"schedulingPeriod":"1 min","schedulingStrategy":"TIMER_DRIVEN","executionNode":"ALL","penaltyDuration":"30 sec","yieldDuration":"1 sec","bulletinLevel":"WARN","runDurationMillis":0,"concurrentlySchedulableTaskCount":1,"autoTerminatedRelationships":[],"scheduledState":"ENABLED","retryCount":10,"retriedRelationships":[],"backoffMechanism":"PENALIZE_FLOWFILE","maxBackoffPeriod":"10 mins","componentType":"PROCESSOR","groupIdentifier":"2ecb96c9-8f15-384f-8cc3-87b24e77c57c"},{"identifier":"892991e5-3cc0-3477-aad6-0220b2d3447b","instanceIdentifier":"b5725891-0199-1000-4fa5-f37f9cb37d58","name":"Increment Retry Count","comments":"","position":{"x":768.0,"y":376.0},"type":"org.apache.nifi.processors.attributes.UpdateAttribute","bundle":{"group":"org.apache.nifi","artifact":"nifi-update-attribute-nar","version":"2.5.0"},"properties":{"Delete Attributes Expression":null,"Store State":"Do not store state","canonical-value-lookup-cache-size":"100","retry.count":"${retry.count:plus(1)}","Stateful Variables Initial Value":null},"propertyDescriptors":{"Delete Attributes Expression":{"name":"Delete Attributes Expression","displayName":"Delete Attributes Expression","identifiesControllerService":false,"sensitive":false,"dynamic":false},"Store State":{"name":"Store State","displayName":"Store State","identifiesControllerService":false,"sensitive":false,"dynamic":false},"canonical-value-lookup-cache-size":{"name":"canonical-value-lookup-cache-size","displayName":"Cache Value Lookup Cache Size","identifiesControllerService":false,"sensitive":false,"dynamic":false},"retry.count":{"name":"retry.count","displayName":"retry.count","identifiesControllerService":false,"sensitive":false,"dynamic":true},"Stateful Variables Initial Value":{"name":"Stateful Variables Initial Value","displayName":"Stateful Variables Initial Value","identifiesControllerService":false,"sensitive":false,"dynamic":false}},"style":{},"schedulingPeriod":"0 sec","schedulingStrategy":"TIMER_DRIVEN","executionNode":"ALL","penaltyDuration":"30 sec","yieldDuration":"1 sec","bulletinLevel":"WARN","runDurationMillis":25,"concurrentlySchedulableTaskCount":1,"autoTerminatedRelationships":[],"scheduledState":"ENABLED","retryCount":10,"retriedRelationships":[],"backoffMechanism":"PENALIZE_FLOWFILE","maxBackoffPeriod":"10 mins","componentType":"PROCESSOR","groupIdentifier":"2ecb96c9-8f15-384f-8cc3-87b24e77c57c"},{"identifier":"436946dc-5ddd-307f-91a6-824d4bd8e849","instanceIdentifier":"b56e63c0-0199-1000-696e-aabccbe7b220","name":"UpdateAttribute","comments":"","position":{"x":296.0000258734601,"y":-89.79996708696319},"type":"org.apache.nifi.processors.attributes.UpdateAttribute","bundle":{"group":"org.apache.nifi","artifact":"nifi-update-attribute-nar","version":"2.5.0"},"properties":{"hdfs_path":"/data/files/gemini/${now():format('yyyy-MM-dd')}","Delete Attributes Expression":null,"filename":"${path:substringAfterLast('/'):trim()}_${filename}","Store State":"Do not store state","canonical-value-lookup-cache-size":"100","city":"${absolute.path:replace('\\', '/'):substringBeforeLast('/')}","state":"${path:replace('\\', '/'):substringBeforeLast('/')}","Stateful Variables Initial Value":null},"propertyDescriptors":{"hdfs_path":{"name":"hdfs_path","displayName":"hdfs_path","identifiesControllerService":false,"sensitive":false,"dynamic":true},"Delete Attributes Expression":{"name":"Delete Attributes Expression","displayName":"Delete Attributes Expression","identifiesControllerService":false,"sensitive":false,"dynamic":false},"filename":{"name":"filename","displayName":"filename","identifiesControllerService":false,"sensitive":false,"dynamic":true},"Store State":{"name":"Store State","displayName":"Store State","identifiesControllerService":false,"sensitive":false,"dynamic":false},"canonical-value-lookup-cache-size":{"name":"canonical-value-lookup-cache-size","displayName":"Cache Value Lookup Cache Size","identifiesControllerService":false,"sensitive":false,"dynamic":false},"city":{"name":"city","displayName":"city","identifiesControllerService":false,"sensitive":false,"dynamic":true},"state":{"name":"state","displayName":"state","identifiesControllerService":false,"sensitive":false,"dynamic":true},"Stateful Variables Initial Value":{"name":"Stateful Variables Initial Value","displayName":"Stateful Variables Initial Value","identifiesControllerService":false,"sensitive":false,"dynamic":false}},"style":{},"schedulingPeriod":"0 sec","schedulingStrategy":"TIMER_DRIVEN","executionNode":"ALL","penaltyDuration":"30 sec","yieldDuration":"1 sec","bulletinLevel":"WARN","runDurationMillis":25,"concurrentlySchedulableTaskCount":1,"autoTerminatedRelationships":[],"scheduledState":"ENABLED","retryCount":10,"retriedRelationships":[],"backoffMechanism":"PENALIZE_FLOWFILE","maxBackoffPeriod":"10 mins","componentType":"PROCESSOR","groupIdentifier":"2ecb96c9-8f15-384f-8cc3-87b24e77c57c"},{"identifier":"2365549d-a030-3a3f-96d9-99fbd36b53c5","instanceIdentifier":"b56d383c-0199-1000-daed-9eb594f518fd","name":"FetchFile","comments":"","position":{"x":-183.99997412653988,"y":91.20003291303681},"type":"org.apache.nifi.processors.standard.FetchFile","bundle":{"group":"org.apache.nifi","artifact":"nifi-standard-nar","version":"2.5.0"},"properties":{"Move Conflict Strategy":"Rename","Log level when file not found":"ERROR","Move Destination Directory":null,"Log level when permission denied":"ERROR","File to Fetch":"${absolute.path}/${filename}","Completion Strategy":"None"},"propertyDescriptors":{"Move Conflict Strategy":{"name":"Move Conflict Strategy","displayName":"Move Conflict Strategy","identifiesControllerService":false,"sensitive":false,"dynamic":false},"Log level when file not found":{"name":"Log level when file not found","displayName":"Log level when file not found","identifiesControllerService":false,"sensitive":false,"dynamic":false},"Move Destination Directory":{"name":"Move Destination Directory","displayName":"Move Destination Directory","identifiesControllerService":false,"sensitive":false,"dynamic":false},"Log level when permission denied":{"name":"Log level when permission denied","displayName":"Log level when permission denied","identifiesControllerService":false,"sensitive":false,"dynamic":false},"File to Fetch":{"name":"File to Fetch","displayName":"File to Fetch","identifiesControllerService":false,"sensitive":false,"dynamic":false},"Completion Strategy":{"name":"Completion Strategy","displayName":"Completion Strategy","identifiesControllerService":false,"sensitive":false,"dynamic":false}},"style":{},"schedulingPeriod":"0 sec","schedulingStrategy":"TIMER_DRIVEN","executionNode":"ALL","penaltyDuration":"30 sec","yieldDuration":"1 sec","bulletinLevel":"WARN","runDurationMillis":0,"concurrentlySchedulableTaskCount":1,"autoTerminatedRelationships":[],"scheduledState":"ENABLED","retryCount":10,"retriedRelationships":[],"backoffMechanism":"PENALIZE_FLOWFILE","maxBackoffPeriod":"10 mins","componentType":"PROCESSOR","groupIdentifier":"2ecb96c9-8f15-384f-8cc3-87b24e77c57c"},{"identifier":"8a0825b9-f290-389f-969b-d798c5964de1","instanceIdentifier":"b5750cdd-0199-1000-9b01-f51a838ae052","name":"ReplaceText","comments":"","position":{"x":-192.0,"y":792.0},"type":"org.apache.nifi.processors.standard.ReplaceText","bundle":{"group":"org.apache.nifi","artifact":"nifi-standard-nar","version":"2.5.0"},"properties":{"Regular Expression":"(?s)(^.*$)","Replacement Value":"File: ${filename}, Path: ${path}, Reason: Failed to transfer, Timestamp: ${now()}\\n","Evaluation Mode":"Line-by-Line","Text to Prepend":null,"Line-by-Line Evaluation Mode":"All","Character Set":"UTF-8","Maximum Buffer Size":"1 MB","Replacement Strategy":"Regex Replace","Text to Append":null},"propertyDescriptors":{"Regular Expression":{"name":"Regular Expression","displayName":"Search Value","identifiesControllerService":false,"sensitive":false,"dynamic":false},"Replacement Value":{"name":"Replacement Value","displayName":"Replacement Value","identifiesControllerService":false,"sensitive":false,"dynamic":false},"Evaluation Mode":{"name":"Evaluation Mode","displayName":"Evaluation Mode","identifiesControllerService":false,"sensitive":false,"dynamic":false},"Text to Prepend":{"name":"Text to Prepend","displayName":"Text to Prepend","identifiesControllerService":false,"sensitive":false,"dynamic":false},"Line-by-Line Evaluation Mode":{"name":"Line-by-Line Evaluation Mode","displayName":"Line-by-Line Evaluation Mode","identifiesControllerService":false,"sensitive":false,"dynamic":false},"Character Set":{"name":"Character Set","displayName":"Character Set","identifiesControllerService":false,"sensitive":false,"dynamic":false},"Maximum Buffer Size":{"name":"Maximum Buffer Size","displayName":"Maximum Buffer Size","identifiesControllerService":false,"sensitive":false,"dynamic":false},"Replacement Strategy":{"name":"Replacement Strategy","displayName":"Replacement Strategy","identifiesControllerService":false,"sensitive":false,"dynamic":false},"Text to Append":{"name":"Text to Append","displayName":"Text to Append","identifiesControllerService":false,"sensitive":false,"dynamic":false}},"style":{},"schedulingPeriod":"0 sec","schedulingStrategy":"TIMER_DRIVEN","executionNode":"ALL","penaltyDuration":"30 sec","yieldDuration":"1 sec","bulletinLevel":"WARN","runDurationMillis":25,"concurrentlySchedulableTaskCount":1,"autoTerminatedRelationships":["failure"],"scheduledState":"ENABLED","retryCount":10,"retriedRelationships":[],"backoffMechanism":"PENALIZE_FLOWFILE","maxBackoffPeriod":"10 mins","componentType":"PROCESSOR","groupIdentifier":"2ecb96c9-8f15-384f-8cc3-87b24e77c57c"},{"identifier":"5fbebaa1-605f-31cb-8ee5-7ce5f7ca7918","instanceIdentifier":"b5731b78-0199-1000-48ef-956e61242ab9","name":"Check Retry Count","comments":"","position":{"x":520.0,"y":560.0},"type":"org.apache.nifi.processors.standard.RouteOnAttribute","bundle":{"group":"org.apache.nifi","artifact":"nifi-standard-nar","version":"2.5.0"},"properties":{"retryable":"${retry.count:le(3)}","Routing Strategy":"Route to Property name"},"propertyDescriptors":{"retryable":{"name":"retryable","displayName":"retryable","identifiesControllerService":false,"sensitive":false,"dynamic":true},"Routing Strategy":{"name":"Routing Strategy","displayName":"Routing Strategy","identifiesControllerService":false,"sensitive":false,"dynamic":false}},"style":{},"schedulingPeriod":"0 sec","schedulingStrategy":"TIMER_DRIVEN","executionNode":"ALL","penaltyDuration":"30 sec","yieldDuration":"1 sec","bulletinLevel":"WARN","runDurationMillis":25,"concurrentlySchedulableTaskCount":1,"autoTerminatedRelationships":[],"scheduledState":"ENABLED","retryCount":10,"retriedRelationships":[],"backoffMechanism":"PENALIZE_FLOWFILE","maxBackoffPeriod":"10 mins","componentType":"PROCESSOR","groupIdentifier":"2ecb96c9-8f15-384f-8cc3-87b24e77c57c"},{"identifier":"8c7aede6-c7b4-38c1-bb51-2e20dd2ee452","instanceIdentifier":"b574c6f9-0199-1000-6f96-c297ca9fc78f","name":"LogAttribute","comments":"","position":{"x":-185.54623751039242,"y":623.4043373700492},"type":"org.apache.nifi.processors.standard.LogAttribute","bundle":{"group":"org.apache.nifi","artifact":"nifi-standard-nar","version":"2.5.0"},"properties":{"Log prefix":null,"character-set":"UTF-8","Log FlowFile Properties":"true","Log Level":"error","attributes-to-ignore-regex":null,"Attributes to Ignore":null,"Attributes to Log":null,"attributes-to-log-regex":".*","Output Format":"Line per Attribute","Log Payload":"false"},"propertyDescriptors":{"Log prefix":{"name":"Log prefix","displayName":"Log prefix","identifiesControllerService":false,"sensitive":false,"dynamic":false},"character-set":{"name":"character-set","displayName":"Character Set","identifiesControllerService":false,"sensitive":false,"dynamic":false},"Log FlowFile Properties":{"name":"Log FlowFile Properties","displayName":"Log FlowFile Properties","identifiesControllerService":false,"sensitive":false,"dynamic":false},"Log Level":{"name":"Log Level","displayName":"Log Level","identifiesControllerService":false,"sensitive":false,"dynamic":false},"attributes-to-ignore-regex":{"name":"attributes-to-ignore-regex","displayName":"Attributes to Ignore by Regular Expression","identifiesControllerService":false,"sensitive":false,"dynamic":false},"Attributes to Ignore":{"name":"Attributes to Ignore","displayName":"Attributes to Ignore","identifiesControllerService":false,"sensitive":false,"dynamic":false},"Attributes to Log":{"name":"Attributes to Log","displayName":"Attributes to Log","identifiesControllerService":false,"sensitive":false,"dynamic":false},"attributes-to-log-regex":{"name":"attributes-to-log-regex","displayName":"Attributes to Log by Regular Expression","identifiesControllerService":false,"sensitive":false,"dynamic":false},"Output Format":{"name":"Output Format","displayName":"Output Format","identifiesControllerService":false,"sensitive":false,"dynamic":false},"Log Payload":{"name":"Log Payload","displayName":"Log Payload","identifiesControllerService":false,"sensitive":false,"dynamic":false}},"style":{},"schedulingPeriod":"0 sec","schedulingStrategy":"TIMER_DRIVEN","executionNode":"ALL","penaltyDuration":"30 sec","yieldDuration":"1 sec","bulletinLevel":"WARN","runDurationMillis":25,"concurrentlySchedulableTaskCount":1,"autoTerminatedRelationships":[],"scheduledState":"ENABLED","retryCount":10,"retriedRelationships":[],"backoffMechanism":"PENALIZE_FLOWFILE","maxBackoffPeriod":"10 mins","componentType":"PROCESSOR","groupIdentifier":"2ecb96c9-8f15-384f-8cc3-87b24e77c57c"},{"identifier":"9fa74818-8038-3bbb-8dfd-1267a1dd3d4b","instanceIdentifier":"b5706ee2-0199-1000-7cb1-e0412ed5b1ee","name":"PutHDFS","comments":"","position":{"x":464.0,"y":176.0},"type":"org.apache.nifi.processors.hadoop.PutHDFS","bundle":{"group":"org.apache.nifi","artifact":"nifi-hadoop-nar","version":"2.5.0"},"properties":{"Permissions umask":null,"Hadoop Configuration Resources":"D:\\Softwares\\hadoop-3.4.1\\etc\\hadoop\\core-site.xml,D:\\Softwares\\hadoop-3.4.1\\etc\\hadoop\\hdfs-site.xml","Remote Owner":null,"Additional Classpath Resources":null,"Resource Transfer Source":"FLOWFILE_CONTENT","Compression codec":"NONE","IO Buffer Size":null,"Remote Group":null,"File Resource Service":null,"Block Size":null,"Ignore Locality":"false","Replication":null,"kerberos-user-service":null,"Append Mode":"DEFAULT","writing-strategy":"writeAndRename","Directory":"${hdfs_path}","Conflict Resolution Strategy":"fail"},"propertyDescriptors":{"Permissions umask":{"name":"Permissions umask","displayName":"Permissions umask","identifiesControllerService":false,"sensitive":false,"dynamic":false},"Hadoop Configuration Resources":{"name":"Hadoop Configuration Resources","displayName":"Hadoop Configuration Resources","identifiesControllerService":false,"sensitive":false,"dynamic":false,"resourceDefinition":{"cardinality":"MULTIPLE","resourceTypes":["FILE"]}},"Remote Owner":{"name":"Remote Owner","displayName":"Remote Owner","identifiesControllerService":false,"sensitive":false,"dynamic":false},"Additional Classpath Resources":{"name":"Additional Classpath Resources","displayName":"Additional Classpath Resources","identifiesControllerService":false,"sensitive":false,"dynamic":false,"resourceDefinition":{"cardinality":"MULTIPLE","resourceTypes":["DIRECTORY","FILE"]}},"Resource Transfer Source":{"name":"Resource Transfer Source","displayName":"Resource Transfer Source","identifiesControllerService":false,"sensitive":false,"dynamic":false},"Compression codec":{"name":"Compression codec","displayName":"Compression codec","identifiesControllerService":false,"sensitive":false,"dynamic":false},"IO Buffer Size":{"name":"IO Buffer Size","displayName":"IO Buffer Size","identifiesControllerService":false,"sensitive":false,"dynamic":false},"Remote Group":{"name":"Remote Group","displayName":"Remote Group","identifiesControllerService":false,"sensitive":false,"dynamic":false},"File Resource Service":{"name":"File Resource Service","displayName":"File Resource Service","identifiesControllerService":true,"sensitive":false,"dynamic":false},"Block Size":{"name":"Block Size","displayName":"Block Size","identifiesControllerService":false,"sensitive":false,"dynamic":false},"Ignore Locality":{"name":"Ignore Locality","displayName":"Ignore Locality","identifiesControllerService":false,"sensitive":false,"dynamic":false},"Replication":{"name":"Replication","displayName":"Replication","identifiesControllerService":false,"sensitive":false,"dynamic":false},"kerberos-user-service":{"name":"kerberos-user-service","displayName":"Kerberos User Service","identifiesControllerService":true,"sensitive":false,"dynamic":false},"Append Mode":{"name":"Append Mode","displayName":"Append Mode","identifiesControllerService":false,"sensitive":false,"dynamic":false},"writing-strategy":{"name":"writing-strategy","displayName":"Writing Strategy","identifiesControllerService":false,"sensitive":false,"dynamic":false},"Directory":{"name":"Directory","displayName":"Directory","identifiesControllerService":false,"sensitive":false,"dynamic":false},"Conflict Resolution Strategy":{"name":"Conflict Resolution Strategy","displayName":"Conflict Resolution Strategy","identifiesControllerService":false,"sensitive":false,"dynamic":false}},"style":{},"schedulingPeriod":"0 sec","schedulingStrategy":"TIMER_DRIVEN","executionNode":"ALL","penaltyDuration":"30 sec","yieldDuration":"1 sec","bulletinLevel":"WARN","runDurationMillis":0,"concurrentlySchedulableTaskCount":1,"autoTerminatedRelationships":["success"],"scheduledState":"ENABLED","retryCount":10,"retriedRelationships":[],"backoffMechanism":"PENALIZE_FLOWFILE","maxBackoffPeriod":"10 mins","componentType":"PROCESSOR","groupIdentifier":"2ecb96c9-8f15-384f-8cc3-87b24e77c57c"}],"inputPorts":[],"outputPorts":[],"connections":[{"identifier":"a7654966-414b-3d86-95c2-f056626a1bd8","instanceIdentifier":"b577429c-0199-1000-fedb-78840fac7a12","name":"","source":{"id":"bac6f558-67b2-3bdf-9b69-c8e552437974","type":"FUNNEL","groupId":"2ecb96c9-8f15-384f-8cc3-87b24e77c57c","name":"Funnel","comments":"","instanceIdentifier":"b5749b0b-0199-1000-566c-94a742e27895"},"destination":{"id":"8c7aede6-c7b4-38c1-bb51-2e20dd2ee452","type":"PROCESSOR","groupId":"2ecb96c9-8f15-384f-8cc3-87b24e77c57c","name":"LogAttribute","comments":"","instanceIdentifier":"b574c6f9-0199-1000-6f96-c297ca9fc78f"},"labelIndex":0,"zIndex":9,"selectedRelationships":[""],"backPressureObjectThreshold":10000,"backPressureDataSizeThreshold":"1 GB","flowFileExpiration":"0 sec","prioritizers":[],"bends":[],"loadBalanceStrategy":"DO_NOT_LOAD_BALANCE","partitioningAttribute":"","loadBalanceCompression":"DO_NOT_COMPRESS","componentType":"CONNECTION","groupIdentifier":"2ecb96c9-8f15-384f-8cc3-87b24e77c57c"},{"identifier":"09a12a6d-f845-30a6-a7d2-a7bbd535f949","instanceIdentifier":"b574112c-0199-1000-d17b-d1de60a56733","name":"","source":{"id":"5fbebaa1-605f-31cb-8ee5-7ce5f7ca7918","type":"PROCESSOR","groupId":"2ecb96c9-8f15-384f-8cc3-87b24e77c57c","name":"Check Retry Count","comments":"","instanceIdentifier":"b5731b78-0199-1000-48ef-956e61242ab9"},"destination":{"id":"9fa74818-8038-3bbb-8dfd-1267a1dd3d4b","type":"PROCESSOR","groupId":"2ecb96c9-8f15-384f-8cc3-87b24e77c57c","name":"PutHDFS","comments":"","instanceIdentifier":"b5706ee2-0199-1000-7cb1-e0412ed5b1ee"},"labelIndex":0,"zIndex":6,"selectedRelationships":["retryable"],"backPressureObjectThreshold":10000,"backPressureDataSizeThreshold":"1 GB","flowFileExpiration":"0 sec","prioritizers":[],"bends":[],"loadBalanceStrategy":"DO_NOT_LOAD_BALANCE","partitioningAttribute":"","loadBalanceCompression":"DO_NOT_COMPRESS","componentType":"CONNECTION","groupIdentifier":"2ecb96c9-8f15-384f-8cc3-87b24e77c57c"},{"identifier":"6b8d3b8b-6f1a-3441-9738-990365fffc8d","instanceIdentifier":"b56e9856-0199-1000-c280-4ac4f990fc17","name":"","source":{"id":"2365549d-a030-3a3f-96d9-99fbd36b53c5","type":"PROCESSOR","groupId":"2ecb96c9-8f15-384f-8cc3-87b24e77c57c","name":"FetchFile","comments":"","instanceIdentifier":"b56d383c-0199-1000-daed-9eb594f518fd"},"destination":{"id":"436946dc-5ddd-307f-91a6-824d4bd8e849","type":"PROCESSOR","groupId":"2ecb96c9-8f15-384f-8cc3-87b24e77c57c","name":"UpdateAttribute","comments":"","instanceIdentifier":"b56e63c0-0199-1000-696e-aabccbe7b220"},"labelIndex":0,"zIndex":2,"selectedRelationships":["success"],"backPressureObjectThreshold":10000,"backPressureDataSizeThreshold":"1 GB","flowFileExpiration":"0 sec","prioritizers":[],"bends":[],"loadBalanceStrategy":"DO_NOT_LOAD_BALANCE","partitioningAttribute":"","loadBalanceCompression":"DO_NOT_COMPRESS","componentType":"CONNECTION","groupIdentifier":"2ecb96c9-8f15-384f-8cc3-87b24e77c57c"},{"identifier":"fee87009-8772-300b-a845-2701e880e886","instanceIdentifier":"b57705f0-0199-1000-3d9f-3311bac5582a","name":"","source":{"id":"5fbebaa1-605f-31cb-8ee5-7ce5f7ca7918","type":"PROCESSOR","groupId":"2ecb96c9-8f15-384f-8cc3-87b24e77c57c","name":"Check Retry Count","comments":"","instanceIdentifier":"b5731b78-0199-1000-48ef-956e61242ab9"},"destination":{"id":"bac6f558-67b2-3bdf-9b69-c8e552437974","type":"FUNNEL","groupId":"2ecb96c9-8f15-384f-8cc3-87b24e77c57c","name":"Funnel","comments":"","instanceIdentifier":"b5749b0b-0199-1000-566c-94a742e27895"},"labelIndex":0,"zIndex":8,"selectedRelationships":["unmatched"],"backPressureObjectThreshold":10000,"backPressureDataSizeThreshold":"1 GB","flowFileExpiration":"0 sec","prioritizers":[],"bends":[],"loadBalanceStrategy":"DO_NOT_LOAD_BALANCE","partitioningAttribute":"","loadBalanceCompression":"DO_NOT_COMPRESS","componentType":"CONNECTION","groupIdentifier":"2ecb96c9-8f15-384f-8cc3-87b24e77c57c"},{"identifier":"163ff676-0a2a-36eb-8924-8ebb4cc05423","instanceIdentifier":"b56e2efc-0199-1000-d73c-3ab3ee62627c","name":"","source":{"id":"3693d146-fa41-3628-9cf0-cb1e64a80b7e","type":"PROCESSOR","groupId":"2ecb96c9-8f15-384f-8cc3-87b24e77c57c","name":"ListFile","comments":"","instanceIdentifier":"b56d2487-0199-1000-a9af-363f0d1c43ff"},"destination":{"id":"2365549d-a030-3a3f-96d9-99fbd36b53c5","type":"PROCESSOR","groupId":"2ecb96c9-8f15-384f-8cc3-87b24e77c57c","name":"FetchFile","comments":"","instanceIdentifier":"b56d383c-0199-1000-daed-9eb594f518fd"},"labelIndex":0,"zIndex":1,"selectedRelationships":["success"],"backPressureObjectThreshold":10000,"backPressureDataSizeThreshold":"1 GB","flowFileExpiration":"0 sec","prioritizers":[],"bends":[],"loadBalanceStrategy":"DO_NOT_LOAD_BALANCE","partitioningAttribute":"","loadBalanceCompression":"DO_NOT_COMPRESS","componentType":"CONNECTION","groupIdentifier":"2ecb96c9-8f15-384f-8cc3-87b24e77c57c"},{"identifier":"ba532ca4-2c8b-329d-99c9-3f441348f325","instanceIdentifier":"b573e8e6-0199-1000-8198-f381ff752347","name":"","source":{"id":"892991e5-3cc0-3477-aad6-0220b2d3447b","type":"PROCESSOR","groupId":"2ecb96c9-8f15-384f-8cc3-87b24e77c57c","name":"Increment Retry Count","comments":"","instanceIdentifier":"b5725891-0199-1000-4fa5-f37f9cb37d58"},"destination":{"id":"5fbebaa1-605f-31cb-8ee5-7ce5f7ca7918","type":"PROCESSOR","groupId":"2ecb96c9-8f15-384f-8cc3-87b24e77c57c","name":"Check Retry Count","comments":"","instanceIdentifier":"b5731b78-0199-1000-48ef-956e61242ab9"},"labelIndex":0,"zIndex":5,"selectedRelationships":["success"],"backPressureObjectThreshold":10000,"backPressureDataSizeThreshold":"1 GB","flowFileExpiration":"0 sec","prioritizers":[],"bends":[],"loadBalanceStrategy":"DO_NOT_LOAD_BALANCE","partitioningAttribute":"","loadBalanceCompression":"DO_NOT_COMPRESS","componentType":"CONNECTION","groupIdentifier":"2ecb96c9-8f15-384f-8cc3-87b24e77c57c"},{"identifier":"eaeb162c-fe8b-320e-94c8-0d1128df707b","instanceIdentifier":"b576de71-0199-1000-886a-e028f70eea0f","name":"","source":{"id":"2365549d-a030-3a3f-96d9-99fbd36b53c5","type":"PROCESSOR","groupId":"2ecb96c9-8f15-384f-8cc3-87b24e77c57c","name":"FetchFile","comments":"","instanceIdentifier":"b56d383c-0199-1000-daed-9eb594f518fd"},"destination":{"id":"bac6f558-67b2-3bdf-9b69-c8e552437974","type":"FUNNEL","groupId":"2ecb96c9-8f15-384f-8cc3-87b24e77c57c","name":"Funnel","comments":"","instanceIdentifier":"b5749b0b-0199-1000-566c-94a742e27895"},"labelIndex":0,"zIndex":7,"selectedRelationships":["failure"],"backPressureObjectThreshold":10000,"backPressureDataSizeThreshold":"1 GB","flowFileExpiration":"0 sec","prioritizers":[],"bends":[],"loadBalanceStrategy":"DO_NOT_LOAD_BALANCE","partitioningAttribute":"","loadBalanceCompression":"DO_NOT_COMPRESS","componentType":"CONNECTION","groupIdentifier":"2ecb96c9-8f15-384f-8cc3-87b24e77c57c"},{"identifier":"6f022f34-4c65-39b0-9542-f4fe80fab22b","instanceIdentifier":"b577f11f-0199-1000-83f1-43b92e39dc87","name":"","source":{"id":"2365549d-a030-3a3f-96d9-99fbd36b53c5","type":"PROCESSOR","groupId":"2ecb96c9-8f15-384f-8cc3-87b24e77c57c","name":"FetchFile","comments":"","instanceIdentifier":"b56d383c-0199-1000-daed-9eb594f518fd"},"destination":{"id":"bac6f558-67b2-3bdf-9b69-c8e552437974","type":"FUNNEL","groupId":"2ecb96c9-8f15-384f-8cc3-87b24e77c57c","name":"Funnel","comments":"","instanceIdentifier":"b5749b0b-0199-1000-566c-94a742e27895"},"labelIndex":0,"zIndex":12,"selectedRelationships":["permission.denied","not.found"],"backPressureObjectThreshold":10000,"backPressureDataSizeThreshold":"1 GB","flowFileExpiration":"0 sec","prioritizers":[],"bends":[{"x":-299.163456813558,"y":252.54574816942696}],"loadBalanceStrategy":"DO_NOT_LOAD_BALANCE","partitioningAttribute":"","loadBalanceCompression":"DO_NOT_COMPRESS","componentType":"CONNECTION","groupIdentifier":"2ecb96c9-8f15-384f-8cc3-87b24e77c57c"},{"identifier":"4783a309-48b4-3f4c-ad8a-22b1553b38d1","instanceIdentifier":"b577613c-0199-1000-1ced-3a28c60016bb","name":"","source":{"id":"8c7aede6-c7b4-38c1-bb51-2e20dd2ee452","type":"PROCESSOR","groupId":"2ecb96c9-8f15-384f-8cc3-87b24e77c57c","name":"LogAttribute","comments":"","instanceIdentifier":"b574c6f9-0199-1000-6f96-c297ca9fc78f"},"destination":{"id":"8a0825b9-f290-389f-969b-d798c5964de1","type":"PROCESSOR","groupId":"2ecb96c9-8f15-384f-8cc3-87b24e77c57c","name":"ReplaceText","comments":"","instanceIdentifier":"b5750cdd-0199-1000-9b01-f51a838ae052"},"labelIndex":0,"zIndex":10,"selectedRelationships":["success"],"backPressureObjectThreshold":10000,"backPressureDataSizeThreshold":"1 GB","flowFileExpiration":"0 sec","prioritizers":[],"bends":[],"loadBalanceStrategy":"DO_NOT_LOAD_BALANCE","partitioningAttribute":"","loadBalanceCompression":"DO_NOT_COMPRESS","componentType":"CONNECTION","groupIdentifier":"2ecb96c9-8f15-384f-8cc3-87b24e77c57c"},{"identifier":"c9a39c6d-054f-3b19-bd35-6ff05a3185a5","instanceIdentifier":"b5776f0a-0199-1000-d846-d7b7bf644005","name":"","source":{"id":"8a0825b9-f290-389f-969b-d798c5964de1","type":"PROCESSOR","groupId":"2ecb96c9-8f15-384f-8cc3-87b24e77c57c","name":"ReplaceText","comments":"","instanceIdentifier":"b5750cdd-0199-1000-9b01-f51a838ae052"},"destination":{"id":"e1d2e942-6fac-3bb8-807b-f6fa80c2cd41","type":"PROCESSOR","groupId":"2ecb96c9-8f15-384f-8cc3-87b24e77c57c","name":"PutFile","comments":"","instanceIdentifier":"b575a029-0199-1000-4567-3787e8702850"},"labelIndex":0,"zIndex":11,"selectedRelationships":["success"],"backPressureObjectThreshold":10000,"backPressureDataSizeThreshold":"1 GB","flowFileExpiration":"0 sec","prioritizers":[],"bends":[],"loadBalanceStrategy":"DO_NOT_LOAD_BALANCE","partitioningAttribute":"","loadBalanceCompression":"DO_NOT_COMPRESS","componentType":"CONNECTION","groupIdentifier":"2ecb96c9-8f15-384f-8cc3-87b24e77c57c"},{"identifier":"95f61900-6619-3822-a9c1-adaff69ee6d5","instanceIdentifier":"b5707c2a-0199-1000-2376-1a1f55478181","name":"","source":{"id":"436946dc-5ddd-307f-91a6-824d4bd8e849","type":"PROCESSOR","groupId":"2ecb96c9-8f15-384f-8cc3-87b24e77c57c","name":"UpdateAttribute","comments":"","instanceIdentifier":"b56e63c0-0199-1000-696e-aabccbe7b220"},"destination":{"id":"9fa74818-8038-3bbb-8dfd-1267a1dd3d4b","type":"PROCESSOR","groupId":"2ecb96c9-8f15-384f-8cc3-87b24e77c57c","name":"PutHDFS","comments":"","instanceIdentifier":"b5706ee2-0199-1000-7cb1-e0412ed5b1ee"},"labelIndex":0,"zIndex":3,"selectedRelationships":["success"],"backPressureObjectThreshold":10000,"backPressureDataSizeThreshold":"1 GB","flowFileExpiration":"0 sec","prioritizers":[],"bends":[],"loadBalanceStrategy":"DO_NOT_LOAD_BALANCE","partitioningAttribute":"","loadBalanceCompression":"DO_NOT_COMPRESS","componentType":"CONNECTION","groupIdentifier":"2ecb96c9-8f15-384f-8cc3-87b24e77c57c"},{"identifier":"a9e6d368-3ec3-34bd-9a91-7e6a96edbe98","instanceIdentifier":"b573d007-0199-1000-2567-08a71dc9d48c","name":"","source":{"id":"9fa74818-8038-3bbb-8dfd-1267a1dd3d4b","type":"PROCESSOR","groupId":"2ecb96c9-8f15-384f-8cc3-87b24e77c57c","name":"PutHDFS","comments":"","instanceIdentifier":"b5706ee2-0199-1000-7cb1-e0412ed5b1ee"},"destination":{"id":"892991e5-3cc0-3477-aad6-0220b2d3447b","type":"PROCESSOR","groupId":"2ecb96c9-8f15-384f-8cc3-87b24e77c57c","name":"Increment Retry Count","comments":"","instanceIdentifier":"b5725891-0199-1000-4fa5-f37f9cb37d58"},"labelIndex":0,"zIndex":4,"selectedRelationships":["failure"],"backPressureObjectThreshold":10000,"backPressureDataSizeThreshold":"1 GB","flowFileExpiration":"0 sec","prioritizers":[],"bends":[],"loadBalanceStrategy":"DO_NOT_LOAD_BALANCE","partitioningAttribute":"","loadBalanceCompression":"DO_NOT_COMPRESS","componentType":"CONNECTION","groupIdentifier":"2ecb96c9-8f15-384f-8cc3-87b24e77c57c"}],"labels":[],"funnels":[{"identifier":"bac6f558-67b2-3bdf-9b69-c8e552437974","instanceIdentifier":"b5749b0b-0199-1000-566c-94a742e27895","position":{"x":-114.3269395005762,"y":325.8914634258171},"componentType":"FUNNEL","groupIdentifier":"2ecb96c9-8f15-384f-8cc3-87b24e77c57c"}],"controllerServices":[],"defaultFlowFileExpiration":"0 sec","defaultBackPressureObjectThreshold":10000,"defaultBackPressureDataSizeThreshold":"1 GB","scheduledState":"ENABLED","executionEngine":"INHERITED","maxConcurrentTasks":1,"statelessFlowTimeout":"1 min","flowFileConcurrency":"UNBOUNDED","flowFileOutboundPolicy":"STREAM_WHEN_AVAILABLE","componentType":"PROCESS_GROUP"},"externalControllerServices":{},"parameterContexts":{},"flowEncodingVersion":"1.0","parameterProviders":{},"latest":false}